{
  "hash": "cd8523fe",
  "configHash": "ada1deb7",
  "lockfileHash": "35c095f2",
  "browserHash": "f6db8dc4",
  "optimized": {
    "vue": {
      "src": "../../../node_modules/.pnpm/vue@3.4.21/node_modules/vue/dist/vue.runtime.esm-bundler.js",
      "file": "vue.js",
      "fileHash": "ab7c6a0b",
      "needsInterop": false
    },
    "vitepress > @vue/devtools-api": {
      "src": "../../../node_modules/.pnpm/@vue+devtools-api@7.0.16_vue@3.4.21/node_modules/@vue/devtools-api/dist/index.js",
      "file": "vitepress___@vue_devtools-api.js",
      "fileHash": "e1b831b0",
      "needsInterop": false
    },
    "vitepress > @vueuse/core": {
      "src": "../../../node_modules/.pnpm/@vueuse+core@10.9.0_vue@3.4.21/node_modules/@vueuse/core/index.mjs",
      "file": "vitepress___@vueuse_core.js",
      "fileHash": "4b000757",
      "needsInterop": false
    }
  },
  "chunks": {
    "chunk-OOO2W3XR": {
      "file": "chunk-OOO2W3XR.js"
    }
  }
}